[
    {
        "id": "915b259c2627e496",
        "type": "tab",
        "label": "Flow 1",
        "disabled": false,
        "info": "",
        "env": []
    },
    {
        "id": "47aa119d56875c3e",
        "type": "mqtt in",
        "z": "915b259c2627e496",
        "name": "",
        "topic": "4ID3_G8/humidity",
        "qos": "2",
        "datatype": "auto-detect",
        "broker": "1724e35aa46f1353",
        "nl": false,
        "rap": true,
        "rh": 0,
        "inputs": 0,
        "x": 250,
        "y": 140,
        "wires": [
            [
                "0ffb68530d337eb2",
                "f949927cf88490ab"
            ]
        ]
    },
    {
        "id": "0ffb68530d337eb2",
        "type": "debug",
        "z": "915b259c2627e496",
        "name": "debug 1",
        "active": true,
        "tosidebar": true,
        "console": false,
        "tostatus": false,
        "complete": "payload",
        "targetType": "msg",
        "statusVal": "",
        "statusType": "auto",
        "x": 480,
        "y": 140,
        "wires": []
    },
    {
        "id": "f949927cf88490ab",
        "type": "ui_chart",
        "z": "915b259c2627e496",
        "name": "humidity",
        "group": "fbeeb02d77420e0f",
        "order": 0,
        "width": 0,
        "height": 0,
        "label": "chart",
        "chartType": "line",
        "legend": "false",
        "xformat": "HH:mm:ss",
        "interpolate": "linear",
        "nodata": "",
        "dot": true,
        "ymin": "0",
        "ymax": "100",
        "removeOlder": 1,
        "removeOlderPoints": "",
        "removeOlderUnit": "3600",
        "cutout": 0,
        "useOneColor": false,
        "useUTC": false,
        "colors": [
            "#1f77b4",
            "#aec7e8",
            "#ff7f0e",
            "#2ca02c",
            "#98df8a",
            "#d62728",
            "#ff9896",
            "#9467bd",
            "#c5b0d5"
        ],
        "outputs": 1,
        "useDifferentColor": false,
        "className": "",
        "x": 520,
        "y": 240,
        "wires": [
            []
        ]
    },
    {
        "id": "1724e35aa46f1353",
        "type": "mqtt-broker",
        "name": "",
        "broker": "test.mosquitto.org",
        "port": "1883",
        "clientid": "",
        "autoConnect": true,
        "usetls": false,
        "protocolVersion": "4",
        "keepalive": "60",
        "cleansession": true,
        "birthTopic": "",
        "birthQos": "0",
        "birthPayload": "",
        "birthMsg": {},
        "closeTopic": "",
        "closeQos": "0",
        "closePayload": "",
        "closeMsg": {},
        "willTopic": "",
        "willQos": "0",
        "willPayload": "",
        "willMsg": {},
        "userProps": "",
        "sessionExpiry": ""
    },
    {
        "id": "fbeeb02d77420e0f",
        "type": "ui_group",
        "name": "Default",
        "tab": "02d5193e7a5e4a42",
        "order": 1,
        "disp": true,
        "width": "6",
        "collapse": false,
        "className": ""
    },
    {
        "id": "02d5193e7a5e4a42",
        "type": "ui_tab",
        "name": "Home",
        "icon": "dashboard",
        "disabled": false,
        "hidden": false
    }
]